glrlm/__init__.py
glrlm/degree.py
glrlm/glrlm.py
glrlm/model.py
glrlm/normalizer.py
glrlm/operator.py
glrlm-0.1.0.dist-info/LICENSE
glrlm-0.1.0.dist-info/METADATA
glrlm-0.1.0.dist-info/WHEEL
glrlm-0.1.0.dist-info/top_level.txt
glrlm-0.1.0.dist-info/RECORD
